kerasy/LICENSE
kerasy/__init__.py
kerasy/activations.py
kerasy/initializers.py
kerasy/losses.py
kerasy/metrics.py
kerasy/models.py
kerasy/optimizers.py
kerasy/regularizers.py
kerasy/setup.py
kerasy/Bio/__init__.py
kerasy/Bio/alignment.py
kerasy/Bio/factorization.py
kerasy/Bio/maxsets.py
kerasy/Bio/prefix.py
kerasy/Bio/scode.py
kerasy/Bio/second_structure.py
kerasy/Bio/string.py
kerasy/Bio/suffix.py
kerasy/Bio/tandem.py
kerasy/ML/EM.py
kerasy/ML/HMM.py
kerasy/ML/__init__.py
kerasy/ML/_kernel.py
kerasy/ML/boosting.py
kerasy/ML/cluster.py
kerasy/ML/decomposition.py
kerasy/ML/linear.py
kerasy/ML/sampling.py
kerasy/ML/svm.py
kerasy/ML/tree.py
kerasy/clib/__init__.py
kerasy/clib/_cutils.pxd
kerasy/clib/_pyutils.cpython-37m-darwin.so
kerasy/clib/c_decomposition.cpython-37m-darwin.so
kerasy/clib/c_deep.cpython-37m-darwin.so
kerasy/clib/c_hmm.cpython-37m-darwin.so
kerasy/clib/c_kmeans.cpython-37m-darwin.so
kerasy/clib/c_maxsets.cpython-37m-darwin.so
kerasy/clib/c_prefix.cpython-37m-darwin.so
kerasy/clib/c_tandem.cpython-37m-darwin.so
kerasy/clib/setup.old.py
kerasy/clib/setup.py
kerasy/datasets/__init__.py
kerasy/datasets/mnist.py
kerasy/datasets/movebank.py
kerasy/datasets/ncbi.py
kerasy/datasets/zinc.py
kerasy/engine/__init__.py
kerasy/engine/base_layer.py
kerasy/engine/sequential.py
kerasy/layers/__init__.py
kerasy/layers/convolutional.py
kerasy/layers/core.py
kerasy/layers/pooling.py
kerasy/search/Astar.py
kerasy/search/__init__.py
kerasy/search/bloom.py
kerasy/search/debruijn.py
kerasy/search/itemset.py
kerasy/search/smart_pay.py
kerasy/search/trie.py
kerasy/utils/__init__.py
kerasy/utils/bio_utils.py
kerasy/utils/coloring_utils.py
kerasy/utils/deep_utils.py
kerasy/utils/generic_utils.py
kerasy/utils/hash_utils.py
kerasy/utils/metric_utils.py
kerasy/utils/model_select_utils.py
kerasy/utils/monitor_utils.py
kerasy/utils/np_utils.py
kerasy/utils/param_utils.py
kerasy/utils/prepro_utils.py
kerasy/utils/progress_utils.py
kerasy/utils/toydata_utils.py
kerasy-0.7.2.dist-info/LICENSE
kerasy-0.7.2.dist-info/METADATA
kerasy-0.7.2.dist-info/WHEEL
kerasy-0.7.2.dist-info/top_level.txt
kerasy-0.7.2.dist-info/RECORD
