Metadata-Version: 2.1
Name: kerasy
Version: 0.7.2
Summary: A set of python modules for machine learning and data mining especially in the biological field.
Home-page: https://iwasakishuto.github.io/Kerasy/doc
Author: Shuto Iwasaki
Author-email: cabernet.rock@gmail.com
License: MIT
Project-URL: Bug Reports, https://github.com/iwasakishuto/Kerasy/issues
Project-URL: Documentation, https://iwasakishuto.github.io/Kerasy/doc/index.html
Project-URL: Source Code, https://github.com/iwasakishuto/Kerasy
Project-URL: Say Thanks!, https://iwasakishuto.github.io/
Platform: UNKNOWN
Classifier: Development Status :: 3 - Alpha
Classifier: Intended Audience :: Developers
Classifier: Intended Audience :: Science/Research
Classifier: Topic :: Scientific/Engineering :: Bio-Informatics
Classifier: Topic :: Software Development :: Libraries
Classifier: Topic :: Software Development :: Libraries :: Python Modules
Classifier: License :: OSI Approved :: MIT License
Classifier: Programming Language :: Python :: 3
Classifier: Programming Language :: Python :: 3.6
Requires-Python: >=3.6
Requires-Dist: numpy (>=1.15.1)
Requires-Dist: scipy (>=1.4.1)
Requires-Dist: seaborn (>=0.10.0)
Requires-Dist: Cython (>=0.28.5)
Requires-Dist: pydotplus (>=2.0.2)
Requires-Dist: bitarray (>=0.8.1)
Requires-Dist: ipython (>=7.15.0)
Provides-Extra: tests
Requires-Dist: pytest ; extra == 'tests'
